{"cameraMode":{"drawMode":0,"name":"Shaded","section":"Shading Mode"},"sceneLighting":true,"audioPlay":false,"sceneViewState":{"m_AlwaysRefresh":false,"showFog":true,"showSkybox":true,"showFlares":true,"showImageEffects":true,"showParticleSystems":true,"showVisualEffectGraphs":true,"m_FxEnabled":true},"in2DMode":false,"pivot":{"x":-20.434019088745118,"y":-213.3699951171875,"z":596.1240844726563},"rotation":{"x":0.33448469638824465,"y":0.07903268188238144,"z":-0.028162524104118348,"w":0.9386661648750305},"size":401.236083984375,"orthographic":false}